xbundle
