Metadata-Version: 1.1
Name: xbundle
Version: 0.3.1
Summary: Converts edX courses between OLX and single-XML formats.
Home-page: https://github.com/mitodl/xbundle
Author: MIT ODL Engineering
Author-email: odl-engineering@mit.edu
License: BSD
Platform: UNKNOWN
Classifier: Programming Language :: Python :: 2
Classifier: Programming Language :: Python :: 3
Classifier: Development Status :: 2 - Pre-Alpha
Classifier: Intended Audience :: Developers
Classifier: Intended Audience :: Education
